README.md
setup.cfg
setup.py
boxrec/__init__.py
boxrec/data_access.py
boxrec/models.py
boxrec/parsers.py
boxrec/services.py
boxrec.egg-info/PKG-INFO
boxrec.egg-info/SOURCES.txt
boxrec.egg-info/dependency_links.txt
boxrec.egg-info/requires.txt
boxrec.egg-info/top_level.txt