Metadata-Version: 1.0
Name: boxrec
Version: 0.1
Summary: A wrapper around the Boxrec.com website to facilitate easy scraping.
Home-page: https://github.com/FutureFacts/boxrec
Author: Floris Hoogenboom, Tom Rijntjes
Author-email: floris.hoogenboom@futurefacts.nl, tom.rijntjes@futurefacts.nl
License: MIT
Platform: UNKNOWN
